{
    "time_created": "2023-10-05T15:12:56",
    "detected_objects": [
        {
            "name": "coke",
            "class": 0,
            "confidence": 0.9999814033508301
        },
        {
            "name": "mountain_dew",
            "class": 1,
            "confidence": 0.99592125415802
        }
    ],
    "all_products": [
        "mountain_dew",
        "other",
        "pocari",
        "coke"
    ],
    "available_products": [
        "coke",
        "mountain_dew"
    ],
    "missing_products": [
        "other",
        "pocari"
    ]
}
